pyeasyal/__init__.py
pyeasyal/core.py
pyeasyal-0.1.1.dist-info/licenses/LICENSE
pyeasyal-0.1.1.dist-info/METADATA
pyeasyal-0.1.1.dist-info/WHEEL
pyeasyal-0.1.1.dist-info/top_level.txt
pyeasyal-0.1.1.dist-info/RECORD
